firecore_config/__init__.py
firecore_config/_config.py
firecore_config-0.1.0.dist-info/METADATA
firecore_config-0.1.0.dist-info/WHEEL
firecore_config-0.1.0.dist-info/entry_points.txt
firecore_config-0.1.0.dist-info/RECORD
